langchain_risinglight/__init__.py
langchain_risinglight-0.1.0.dist-info/LICENSE
langchain_risinglight-0.1.0.dist-info/METADATA
langchain_risinglight-0.1.0.dist-info/WHEEL
langchain_risinglight-0.1.0.dist-info/RECORD
