Metadata-Version: 2.1
Name: langchain-risinglight
Version: 0.1.0
Summary: Langchain binding for RisingLight
License: MIT
Author: Alex Chi Z
Author-email: iskyzh@gmail.com
Requires-Python: >=3.10,<3.13
Classifier: License :: OSI Approved :: MIT License
Classifier: Programming Language :: Python :: 3
Classifier: Programming Language :: Python :: 3.10
Classifier: Programming Language :: Python :: 3.11
Classifier: Programming Language :: Python :: 3.12
Requires-Dist: langchain (>=0.3.14,<0.4.0)
